latex_table_image/Ex1.py
latex_table_image/Ex2.py
latex_table_image/__init__.py
latex_table_and_image-0.0.2.dist-info/METADATA
latex_table_and_image-0.0.2.dist-info/WHEEL
latex_table_and_image-0.0.2.dist-info/top_level.txt
latex_table_and_image-0.0.2.dist-info/RECORD
